bigO-0.2.dist-info/METADATA
bigO-0.2.dist-info/metadata.json
bigO-0.2.dist-info/DESCRIPTION.rst
bigO-0.2.dist-info/top_level.txt
bigO-0.2.dist-info/RECORD
bigO-0.2.dist-info/WHEEL
bigO/__init__.py
